pydbfusion.py
pydbfusion-0.1.1.dist-info/METADATA
pydbfusion-0.1.1.dist-info/WHEEL
pydbfusion-0.1.1.dist-info/top_level.txt
pydbfusion-0.1.1.dist-info/RECORD
