Metadata-Version: 2.4
Name: pydbfusion
Version: 0.1.1
Summary: Minimal universal database connection library for SQLite, PostgreSQL, MySQL and Azure SQL database.
Author-email: Tejashree Thete <thetetejashree@gmail.com>
License: MIT
Requires-Python: >=3.8
Requires-Dist: psycopg2-binary>=2.9
Requires-Dist: pymysql>=1.0
Requires-Dist: cryptography>=41.0
Requires-Dist: pyodbc
